ogonek/Ogonek.py
ogonek/__init__.py
Ogonek-1.0.0.dist-info/LICENSE
Ogonek-1.0.0.dist-info/METADATA
Ogonek-1.0.0.dist-info/WHEEL
Ogonek-1.0.0.dist-info/top_level.txt
Ogonek-1.0.0.dist-info/RECORD
