Metadata-Version: 2.1
Name: Ogonek
Version: 1.0.0
Summary: An online library for hashing, licensing and protecting your programs, which includes homemade hashing algorithms and other useful functions.
Home-page: https://github.com/ModerkaScripts/Ogonek
Author: ttwiz_z
Author-email: moderkascriptsltd@gmail.com
Project-URL: Author, https://github.com/ttwizz
Project-URL: Organization, https://github.com/ModerkaScripts
Keywords: Ogonek
Classifier: Programming Language :: Python :: 3.10
Classifier: License :: OSI Approved :: MIT License
Classifier: Operating System :: OS Independent
Requires-Python: >=3.8
License-File: LICENSE
Requires-Dist: requests >=2.31.0
